bucrawlershittt/__init__.py
bucrawlershittt/tag_counter.py
bucrawlershittt-0.0.13.dist-info/LICENSE
bucrawlershittt-0.0.13.dist-info/METADATA
bucrawlershittt-0.0.13.dist-info/WHEEL
bucrawlershittt-0.0.13.dist-info/top_level.txt
bucrawlershittt-0.0.13.dist-info/RECORD
