Metadata-Version: 2.1
Name: bucrawlershittt
Version: 0.0.13
Summary: shitty city boh
Home-page: UNKNOWN
Author: bucrawler man
Author-email: bucucu@gmail.com
License: UNKNOWN
Keywords: python
Platform: UNKNOWN
Classifier: Development Status :: 1 - Planning
Classifier: Intended Audience :: Developers
Classifier: Programming Language :: Python :: 3
Classifier: Operating System :: Unix
Classifier: Operating System :: MacOS :: MacOS X
Classifier: Operating System :: Microsoft :: Windows
License-File: LICENSE
Requires-Dist: requests
